{
    "compare_date": "2018-09-24 22:37:01",
    "last_update": "2018-09-25 08:57:10",
    "nontop_voters": 245,
    "specials": {
        "LEON": 364
    },
    "total_voters": 677,
    "votes": [
        [
            "Alan Wake",
            140,
            "+22"
        ],
        [
            "Alien Isolation",
            333,
            "+31"
        ],
        [
            "Corpse Party",
            314,
            "+38"
        ],
        [
            "Dead Space 1",
            305,
            "+27"
        ],
        [
            "Deadly Premonition",
            141,
            "+31"
        ],
        [
            "FEAR",
            124,
            "+22"
        ],
        [
            "Ghost Trick",
            193,
            "+21"
        ],
        [
            "Grim Fandango",
            182,
            "+15"
        ],
        [
            "I Have No Mouth And I Must Scream",
            393,
            "+32"
        ],
        [
            "Luigi's Mansion",
            340,
            "+35"
        ],
        [
            "Metro 2033",
            272,
            "+40"
        ],
        [
            "Night in the Woods",
            276,
            "+28"
        ],
        [
            "Oxenfree",
            230,
            "+26"
        ],
        [
            "Pony Island",
            195,
            "+24"
        ],
        [
            "Resident Evil 4",
            170,
            "+23"
        ],
        [
            "SCP \u2013 Containment Breach",
            233,
            "+14"
        ],
        [
            "Silent Hill 1 + 2",
            468,
            "+52"
        ],
        [
            "Spooky's Jump Scare Mansion",
            121,
            "+14"
        ],
        [
            "Until Dawn",
            492,
            "+54"
        ],
        [
            "Yume Nikki",
            227,
            "+26"
        ]
    ]
}